
[
{
    "id": "1",
    "name": "Chuch Norris et le Chat noir",
    "description" : "Quand Chuck Norris rencontre un chat noir en début de matinée, c’est le chat qui va passer une sale journée."
},
{
    "id": "2",
    "name": "Chuck Norris-Livret",
    "description": "Chuck Norris n’a pas de livret bancaire.Chuck Norris n’épargne rien."
},
{
    "id": "3",
    "name" : "Chuck Norris aux toilettes",
    "description" : "Quand Chuck Norris va aux toilettes, il y a toujours du papier. Chuck Norris n’est jamais au bout du rouleau."
},
{
    "id": "4",
    "name" : "Chuck Norris et les échos",
    "description" : "Lorsque Chuck Norris crie au bord d’une falaise, il n’y a pas d’écho. On ne répond pas à Chuck Norris."
},
{
    "id": "5",
    "name" : "Chuck Norris et les échos",
    "description" : "Le calendrier de Chuck Norris passe du 31 mars au 2 avril. Personne ne fait de blague à Chuck ."
}
]

